{"hirdetmenyDTO":{"erkeztetesiSzam":null,"origErkeztetesiSzam":null,"feltoltesDatuma":null,"torolveDate":null,"forrasIntezmenyNeve":"Tiszafüredi Polgármesteri Hivatal","forrasIntezmenyOsztaly":null,"forrasIntezmenyCsoport":null,"forrasIntezmenyCime":"5350 Tiszafüred, Fő utca 1. ","forrasIntezmenyTelefon":"59510505","forrasIntezmenyFax":null,"forrasIntezmenyEmail":"jegyzoireferens@tiszafured.hu","ugyintezoNeve":null,"ugyintezoTelefon":null,"ugyintezoFax":null,"ugyintezoEmail":null,"eljaroHatosagNeve":null,"eljaroHatosagCime":null,"kerelmezoNeve":null,"kerelmezoCime":null,"ugyiratszam":"TIS/8664/2026","iktatasiszam":null,"kifuggesztesNapja":"2026-07-07T22:00:00.000+00:00","lejaratNapja":"2026-08-06T22:00:00.000+00:00","kifuggesztesHelye":"Tiszafüred","targy":"Adás-vétel - Tiszafüred hrsz.: 0401/4","kategoria":"Föld","torzsSzoveg":null},"tipus":"foldelovasarlasos","altipus":"adás-vételére","attributumok":{"f_targy1":"adás-vétel szerződés hirdetményi úton történő közlése","helyrajzi_szam1":"0401/4","muvelesi_ag1":"erdő","telepules1":"Tiszafüred","terulet1":"108008 m2","tipus1":"adás-vételére","tulhanyad1":"1/1","vetelar1":"10.800.000.-Ft"},"figyelemFelhivas":null,"csatolmanyok":[{"fajlNev":"TIS-8664-2026.PDF","id":1055970}]}