{"hirdetmenyDTO":{"erkeztetesiSzam":null,"origErkeztetesiSzam":null,"feltoltesDatuma":null,"torolveDate":null,"forrasIntezmenyNeve":"Telkibányai Közös Önkormányzati Hivatal","forrasIntezmenyOsztaly":null,"forrasIntezmenyCsoport":null,"forrasIntezmenyCime":"3896 Telkibánya, Nagy út 2.. ","forrasIntezmenyTelefon":"46388502","forrasIntezmenyFax":"46388502","forrasIntezmenyEmail":"tbanyahivatal@gmail.com","ugyintezoNeve":null,"ugyintezoTelefon":null,"ugyintezoFax":null,"ugyintezoEmail":null,"eljaroHatosagNeve":null,"eljaroHatosagCime":null,"kerelmezoNeve":null,"kerelmezoCime":null,"ugyiratszam":"P/268/2026.","iktatasiszam":"P/268/2026.","kifuggesztesNapja":"2026-07-12T22:00:00.000+00:00","lejaratNapja":"2026-08-11T22:00:00.000+00:00","kifuggesztesHelye":"Pányok Község Önkormányzata","targy":"Adás-vétel - Pányok, külterület hrsz.: 028/1|Adás-vétel - Pányok, külterület hrsz.: 028/1|Adás-vétel - Pányok, külterület hrsz.: 028/1","kategoria":"Föld","torzsSzoveg":null},"tipus":"foldelovasarlasos","altipus":"adás-vételére","attributumok":{"f_targy1":"adás-vétel szerződés hirdetményi úton történő közlése","f_targy2":"adás-vétel szerződés hirdetményi úton történő közlése","f_targy3":"adás-vétel szerződés hirdetményi úton történő közlése","helyrajzi_szam1":"028/1","helyrajzi_szam2":"028/1","helyrajzi_szam3":"028/1","muvelesi_ag1":"erdő","muvelesi_ag2":"erdő","muvelesi_ag3":"erdő","telepules1":"Pányok, külterület","telepules2":"Pányok, külterület","telepules3":"Pányok, külterület","terulet1":"48ha 7159m2","terulet2":"48ha 7159m2","terulet3":"48ha 7159m2","tipus1":"adás-vételére","tipus2":"adás-vételére","tipus3":"adás-vételére","tulhanyad1":"297041/14225345","tulhanyad2":"148520/14225345","tulhanyad3":"148521/14225345","vetelar1":"1.017.000.-Ft","vetelar2":"500.000.-Ft","vetelar3":"500.000.-Ft"},"figyelemFelhivas":null,"csatolmanyok":[{"fajlNev":"Szab_En_-Iv_n_I.-_Iv_n_E.-Iv_n_In_-Kov_cs_G.Tn_-ad_sv_teli_szerz..pdf","id":1056644}]}