{"hirdetmenyDTO":{"erkeztetesiSzam":null,"origErkeztetesiSzam":null,"feltoltesDatuma":null,"torolveDate":null,"forrasIntezmenyNeve":"Szomolya Község Önkormányzata","forrasIntezmenyOsztaly":null,"forrasIntezmenyCsoport":null,"forrasIntezmenyCime":"3411 Szomolya, Szabadság  tér 1. ","forrasIntezmenyTelefon":"49526000","forrasIntezmenyFax":null,"forrasIntezmenyEmail":"pmhszomolya@t-online.hu","ugyintezoNeve":null,"ugyintezoTelefon":null,"ugyintezoFax":null,"ugyintezoEmail":null,"eljaroHatosagNeve":null,"eljaroHatosagCime":null,"kerelmezoNeve":null,"kerelmezoCime":null,"ugyiratszam":"SZO/723/2026","iktatasiszam":"SZO/723-1/2026","kifuggesztesNapja":"2026-07-09T22:00:00.000+00:00","lejaratNapja":"2026-08-09T22:00:00.000+00:00","kifuggesztesHelye":"Szomolya Község Önkormányzata","targy":"Adás-vétel - Szomolya hrsz.: 0328|Adás-vétel - Szomolya hrsz.: 0352|Adás-vétel - Szomolya hrsz.: 0334|Adás-vétel - Szomolya hrsz.: 0349|Adás-vétel - Szomolya hrsz.: 0321|Adás-vétel - Szomolya hrsz.: 0353|Adás-vétel - Szomolya hrsz.: 0450","kategoria":"Föld","torzsSzoveg":null},"tipus":"foldelovasarlasos","altipus":"adás-vételére","attributumok":{"f_targy1":"adás-vétel szerződés hirdetményi úton történő közlése","f_targy2":"adás-vétel szerződés hirdetményi úton történő közlése","f_targy3":"adás-vétel szerződés hirdetményi úton történő közlése","f_targy4":"adás-vétel szerződés hirdetményi úton történő közlése","f_targy5":"adás-vétel szerződés hirdetményi úton történő közlése","f_targy6":"adás-vétel szerződés hirdetményi úton történő közlése","f_targy7":"adás-vétel szerződés hirdetményi úton történő közlése","helyrajzi_szam1":"0328","helyrajzi_szam2":"0352","helyrajzi_szam3":"0334","helyrajzi_szam4":"0349","helyrajzi_szam5":"0321","helyrajzi_szam6":"0353","helyrajzi_szam7":"0450","muvelesi_ag1":"gyümölcsös","muvelesi_ag2":"gyümölcsös","muvelesi_ag3":"gyümölcsös","muvelesi_ag4":"gyümölcsös","muvelesi_ag5":"gyümölcsös","muvelesi_ag6":"gyümölcsös","muvelesi_ag7":"gyümölcsös","telepules1":"Szomolya","telepules2":"Szomolya","telepules3":"Szomolya","telepules4":"Szomolya","telepules5":"Szomolya","telepules6":"Szomolya","telepules7":"Szomolya","terulet1":"295 m2","terulet2":"798 m2","terulet3":"295 m2","terulet4":"799 m2","terulet5":"295 m2","terulet6":"799 m2","terulet7":"799 m2","tipus1":"adás-vételére","tipus2":"adás-vételére","tipus3":"adás-vételére","tipus4":"adás-vételére","tipus5":"adás-vételére","tipus6":"adás-vételére","tipus7":"adás-vételére","tulhanyad1":"1/1","tulhanyad2":"1/1","tulhanyad3":"1/1","tulhanyad4":"1/1","tulhanyad5":"1/1","tulhanyad6":"1/1","tulhanyad7":"1/1","vetelar1":"10.000 Ft","vetelar2":"90.000 Ft","vetelar3":"10.000 Ft","vetelar4":"90.000 Ft","vetelar5":"10.000 Ft","vetelar6":"90.000 Ft","vetelar7":"100.000 Ft"},"figyelemFelhivas":null,"csatolmanyok":[{"fajlNev":"SZO7232026.pdf","id":1056342}]}