{"hirdetmenyDTO":{"erkeztetesiSzam":null,"origErkeztetesiSzam":null,"feltoltesDatuma":null,"torolveDate":null,"forrasIntezmenyNeve":"Kiskőrösi Polgármesteri Hivatal","forrasIntezmenyOsztaly":"Közigazgatási Osztály","forrasIntezmenyCsoport":null,"forrasIntezmenyCime":"6200 Kiskőrös, Petőfi Sándor tér 1.. ","forrasIntezmenyTelefon":"78513120","forrasIntezmenyFax":null,"forrasIntezmenyEmail":"arizs.alexandra@kiskoros.hu","ugyintezoNeve":null,"ugyintezoTelefon":null,"ugyintezoFax":null,"ugyintezoEmail":null,"eljaroHatosagNeve":null,"eljaroHatosagCime":null,"kerelmezoNeve":null,"kerelmezoCime":null,"ugyiratszam":"7246/2026.","iktatasiszam":null,"kifuggesztesNapja":"2026-07-12T22:00:00.000+00:00","lejaratNapja":"2026-08-11T22:00:00.000+00:00","kifuggesztesHelye":"Kiskőrös","targy":"Adás-vétel - Kiskőrös hrsz.: 0351/37","kategoria":"Föld","torzsSzoveg":null},"tipus":"foldelovasarlasos","altipus":"adás-vételére","attributumok":{"f_targy1":"adás-vétel szerződés hirdetményi úton történő közlése","helyrajzi_szam1":"0351/37","muvelesi_ag1":"szőlő","telepules1":"Kiskőrös","terulet1":"5802 m2","tipus1":"adás-vételére","tulhanyad1":"1/1","vetelar1":"4.000.000.- forint"},"figyelemFelhivas":null,"csatolmanyok":[{"fajlNev":"20260713_Kiskoros_0351_37_hsz_AV.pdf","id":1056450}]}