{"hirdetmenyDTO":{"erkeztetesiSzam":null,"origErkeztetesiSzam":null,"feltoltesDatuma":null,"torolveDate":null,"forrasIntezmenyNeve":"Mérai Közös Önkormányzati Hivatal","forrasIntezmenyOsztaly":null,"forrasIntezmenyCsoport":null,"forrasIntezmenyCime":"3871 Méra, Fő út 1.. ","forrasIntezmenyTelefon":"46460101","forrasIntezmenyFax":null,"forrasIntezmenyEmail":"postmaster@phmera.t-online.hu","ugyintezoNeve":null,"ugyintezoTelefon":null,"ugyintezoFax":null,"ugyintezoEmail":null,"eljaroHatosagNeve":null,"eljaroHatosagCime":null,"kerelmezoNeve":null,"kerelmezoCime":null,"ugyiratszam":"MKOH/64/2026","iktatasiszam":"MKOH/64/2026","kifuggesztesNapja":"2026-07-15T22:00:00.000+00:00","lejaratNapja":"2026-08-16T22:00:00.000+00:00","kifuggesztesHelye":"Fulókércs Község Önkormányzata","targy":"Adás-vétel - Fulókércs hrsz.: 076","kategoria":"Föld","torzsSzoveg":null},"tipus":"foldelovasarlasos","altipus":"adás-vételére","attributumok":{"f_targy1":"adás-vétel szerződés hirdetményi úton történő közlése","helyrajzi_szam1":"076","muvelesi_ag1":"erdő","telepules1":"Fulókércs","terulet1":"44.0182 ha","tipus1":"adás-vételére","tulhanyad1":"552/253536","vetelar1":"64.500.- Ft."},"figyelemFelhivas":null,"csatolmanyok":[{"fajlNev":"Ingatlan_ad_s-v_tel_Ful_k_rcs_076_hrsz.pdf","id":1057337}]}