{"hirdetmenyDTO":{"erkeztetesiSzam":null,"origErkeztetesiSzam":null,"feltoltesDatuma":null,"torolveDate":null,"forrasIntezmenyNeve":"Szerencsi Közös Önkormányzati Hivatal","forrasIntezmenyOsztaly":null,"forrasIntezmenyCsoport":null,"forrasIntezmenyCime":"3900 Szerencs, Rákóczi út 56. ","forrasIntezmenyTelefon":"47565200","forrasIntezmenyFax":null,"forrasIntezmenyEmail":"hivatal@szerencs.hu","ugyintezoNeve":null,"ugyintezoTelefon":null,"ugyintezoFax":null,"ugyintezoEmail":null,"eljaroHatosagNeve":null,"eljaroHatosagCime":null,"kerelmezoNeve":null,"kerelmezoCime":null,"ugyiratszam":"PÜI/3283/2026","iktatasiszam":null,"kifuggesztesNapja":"2026-07-15T22:00:00.000+00:00","lejaratNapja":"2026-08-16T22:00:00.000+00:00","kifuggesztesHelye":"Szerencs","targy":"Adás-vétel - Szerencs hrsz.: 4736","kategoria":"Föld","torzsSzoveg":null},"tipus":"foldelovasarlasos","altipus":"adás-vételére","attributumok":{"f_targy1":"adás-vétel szerződés hirdetményi úton történő közlése","helyrajzi_szam1":"4736","muvelesi_ag1":"rét, szántó, kert és gazdasági épület","telepules1":"Szerencs","terulet1":"3678 m2","tipus1":"adás-vételére","tulhanyad1":"2/10","vetelar1":"500.000 Ft"},"figyelemFelhivas":null,"csatolmanyok":[{"fajlNev":"P_I3283.PDF","id":1057266}]}