{"hirdetmenyDTO":{"erkeztetesiSzam":null,"origErkeztetesiSzam":null,"feltoltesDatuma":null,"torolveDate":null,"forrasIntezmenyNeve":"Nagyberki Közös Önkormányzati Hivatal","forrasIntezmenyOsztaly":null,"forrasIntezmenyCsoport":null,"forrasIntezmenyCime":"7255 Nagyberki, Újváros utca 1. ","forrasIntezmenyTelefon":"82579006","forrasIntezmenyFax":"82579007","forrasIntezmenyEmail":"jegyzoberki@nagyberki.hu","ugyintezoNeve":null,"ugyintezoTelefon":null,"ugyintezoFax":null,"ugyintezoEmail":null,"eljaroHatosagNeve":null,"eljaroHatosagCime":null,"kerelmezoNeve":null,"kerelmezoCime":null,"ugyiratszam":"IGAZG/520/2026","iktatasiszam":"IGAZG/520-2/2026","kifuggesztesNapja":"2026-07-16T22:00:00.000+00:00","lejaratNapja":"2026-08-16T22:00:00.000+00:00","kifuggesztesHelye":"Nagyberki","targy":"Adás-vétel - Nagyberki hrsz.: 1253","kategoria":"Föld","torzsSzoveg":null},"tipus":"foldelovasarlasos","altipus":"adás-vételére","attributumok":{"f_targy1":"adás-vétel szerződés hirdetményi úton történő közlése","helyrajzi_szam1":"1253","muvelesi_ag1":"gyümölcsös, szőlő, szántó, szőlő","telepules1":"Nagyberki","terulet1":"3368 m2","tipus1":"adás-vételére","tulhanyad1":"1/1","vetelar1":"200.000.-Ft"},"figyelemFelhivas":null,"csatolmanyok":[{"fajlNev":"IGAZG_520_2026advet.pdf","id":1057546}]}