{"hirdetmenyDTO":{"erkeztetesiSzam":null,"origErkeztetesiSzam":null,"feltoltesDatuma":null,"torolveDate":null,"forrasIntezmenyNeve":"Oroszlányi KÖH Szákszendi Kirendeltsége","forrasIntezmenyOsztaly":null,"forrasIntezmenyCsoport":null,"forrasIntezmenyCime":"2856 Szákszend, Száki utca 91.. ","forrasIntezmenyTelefon":"34371524","forrasIntezmenyFax":null,"forrasIntezmenyEmail":"hivatal@szakszend.hu","ugyintezoNeve":null,"ugyintezoTelefon":null,"ugyintezoFax":null,"ugyintezoEmail":null,"eljaroHatosagNeve":null,"eljaroHatosagCime":null,"kerelmezoNeve":null,"kerelmezoCime":null,"ugyiratszam":"956/2026","iktatasiszam":"956/2026","kifuggesztesNapja":"2026-07-19T22:00:00.000+00:00","lejaratNapja":"2026-08-18T22:00:00.000+00:00","kifuggesztesHelye":"Szákszend","targy":"Adás-vétel - Szákszend hrsz.: 0202/3|Adás-vétel - Szákszend hrsz.: 0202/4","kategoria":"Föld","torzsSzoveg":null},"tipus":"foldelovasarlasos","altipus":"adás-vételére","attributumok":{"f_targy1":"adás-vétel szerződés hirdetményi úton történő közlése","f_targy2":"adás-vétel szerződés hirdetményi úton történő közlése","helyrajzi_szam1":"0202/3","helyrajzi_szam2":"0202/4","muvelesi_ag1":"szántó","muvelesi_ag2":"szántó","telepules1":"Szákszend","telepules2":"Szákszend","terulet1":"6061","terulet2":"1304 m2","tipus1":"adás-vételére","tipus2":"adás-vételére","tulhanyad1":"1/1","tulhanyad2":"1/1","vetelar1":"1.200.000.-","vetelar2":"250.000.-"},"figyelemFelhivas":null,"csatolmanyok":[{"fajlNev":"SKM_C224e26071718560.pdf","id":1057612}]}