{"hirdetmenyDTO":{"erkeztetesiSzam":null,"origErkeztetesiSzam":null,"feltoltesDatuma":null,"torolveDate":null,"forrasIntezmenyNeve":"Fülei Közös Önkormányzati Hivatal","forrasIntezmenyOsztaly":null,"forrasIntezmenyCsoport":null,"forrasIntezmenyCime":"8157 Füle, Petőfi Sándor utca 22.. ","forrasIntezmenyTelefon":"22576058","forrasIntezmenyFax":null,"forrasIntezmenyEmail":"igazgatas@fule.hu","ugyintezoNeve":null,"ugyintezoTelefon":null,"ugyintezoFax":null,"ugyintezoEmail":null,"eljaroHatosagNeve":null,"eljaroHatosagCime":null,"kerelmezoNeve":null,"kerelmezoCime":null,"ugyiratszam":"F/1132/2026","iktatasiszam":"F/1132-1/2026","kifuggesztesNapja":"2026-07-15T22:00:00.000+00:00","lejaratNapja":"2026-08-16T22:00:00.000+00:00","kifuggesztesHelye":"Füle","targy":"Adás-vétel - Füle hrsz.: 826","kategoria":"Föld","torzsSzoveg":null},"tipus":"foldelovasarlasos","altipus":"adás-vételére","attributumok":{"f_targy1":"adás-vétel szerződés hirdetményi úton történő közlése","helyrajzi_szam1":"826","muvelesi_ag1":"szántó, szőlő","telepules1":"Füle","terulet1":"7091 m2","tipus1":"adás-vételére","tulhanyad1":"8/48","vetelar1":"333.340.- Ft"},"figyelemFelhivas":null,"csatolmanyok":[{"fajlNev":"Kifugg_adasvet_Fule_826_hrsz.pdf","id":1057407}]}