{"hirdetmenyDTO":{"erkeztetesiSzam":null,"origErkeztetesiSzam":null,"feltoltesDatuma":null,"torolveDate":null,"forrasIntezmenyNeve":"Pannonhalmi Polgármesteri Hivatal","forrasIntezmenyOsztaly":null,"forrasIntezmenyCsoport":null,"forrasIntezmenyCime":"9090 Pannonhalma, Dózsa Gy. utca 10. ","forrasIntezmenyTelefon":"96554210","forrasIntezmenyFax":null,"forrasIntezmenyEmail":null,"ugyintezoNeve":null,"ugyintezoTelefon":null,"ugyintezoFax":null,"ugyintezoEmail":null,"eljaroHatosagNeve":null,"eljaroHatosagCime":null,"kerelmezoNeve":null,"kerelmezoCime":null,"ugyiratszam":null,"iktatasiszam":"PPH/1391/2026","kifuggesztesNapja":"2026-07-20T22:00:00.000+00:00","lejaratNapja":"2026-08-19T22:00:00.000+00:00","kifuggesztesHelye":"Pannonhalma","targy":"Adás-vétel - Pannonhalma hrsz.: 0283/42","kategoria":"Föld","torzsSzoveg":null},"tipus":"foldelovasarlasos","altipus":"adás-vételére","attributumok":{"f_targy1":"adás-vétel szerződés hirdetményi úton történő közlése","helyrajzi_szam1":"0283/42","muvelesi_ag1":"szántó","telepules1":"Pannonhalma","terulet1":"3495 m2","tipus1":"adás-vételére","tulhanyad1":"355/500","vetelar1":"1.420.000.- Ft"},"figyelemFelhivas":null,"csatolmanyok":[{"fajlNev":"Pannonhalma_0283_42_hrsz..pdf","id":1057970}]}