{"hirdetmenyDTO":{"erkeztetesiSzam":null,"origErkeztetesiSzam":null,"feltoltesDatuma":null,"torolveDate":null,"forrasIntezmenyNeve":"Dunaföldvár Város Jegyzője","forrasIntezmenyOsztaly":"Városfejlesztési és Műszaki Iroda","forrasIntezmenyCsoport":null,"forrasIntezmenyCime":"7020 Dunaföldvár, Kossuth L. utca 2. ","forrasIntezmenyTelefon":"75541558","forrasIntezmenyFax":"75541558","forrasIntezmenyEmail":"muszak@dunafoldvar.hu","ugyintezoNeve":null,"ugyintezoTelefon":null,"ugyintezoFax":null,"ugyintezoEmail":null,"eljaroHatosagNeve":null,"eljaroHatosagCime":null,"kerelmezoNeve":null,"kerelmezoCime":null,"ugyiratszam":"DFV/2417/2026","iktatasiszam":null,"kifuggesztesNapja":"2026-07-22T22:00:00.000+00:00","lejaratNapja":"2026-08-23T22:00:00.000+00:00","kifuggesztesHelye":"Dunaföldvár Város Önkormányzata","targy":"Adás-vétel - Dunaföldvár hrsz.: 0353/111|Adás-vétel - Dunaföldvár hrsz.: 0353/112","kategoria":"Föld","torzsSzoveg":null},"tipus":"foldelovasarlasos","altipus":"adás-vételére","attributumok":{"f_targy1":"adás-vétel szerződés hirdetményi úton történő közlése","f_targy2":"adás-vétel szerződés hirdetményi úton történő közlése","helyrajzi_szam1":"0353/111","helyrajzi_szam2":"0353/112","muvelesi_ag1":"szántó","muvelesi_ag2":"szántó","telepules1":"Dunaföldvár","telepules2":"Dunaföldvár","terulet1":"1 ha 4710 m2","terulet2":"5692 m2","tipus1":"adás-vételére","tipus2":"adás-vételére","tulhanyad1":"1/1","tulhanyad2":"1/1","vetelar1":"4413000 Ft","vetelar2":"1707600 Ft"},"figyelemFelhivas":null,"csatolmanyok":[{"fajlNev":"Adasvetel_0353_111_112.pdf","id":1058346}]}